dbspypractice/__init__.py
dbspypractice/advanced/__init__.py
dbspypractice/advanced/n1.py
dbspypractice-0.0.1.dist-info/METADATA
dbspypractice-0.0.1.dist-info/WHEEL
dbspypractice-0.0.1.dist-info/top_level.txt
dbspypractice-0.0.1.dist-info/RECORD
