Metadata-Version: 2.4
Name: dbspypractice
Version: 0.0.1
Summary: 파이썬 문법 익히기 문제 풀기
Author-email: dbs556 <using556@gmail.com>
Classifier: Programming Language :: Python :: 3
Classifier: License :: OSI Approved :: MIT License
Classifier: Operating System :: OS Independent
Requires-Python: >=3.8
